myelin/__init__.py
myelin/admin/__init__.py
myelin/admin/myelin_admin.py
myelin/hpo/__init__.py
myelin/metric/__init__.py
myelin/metric/metric_client.py
myelin-0.1.14.dist-info/AUTHORS
myelin-0.1.14.dist-info/LICENSE
myelin-0.1.14.dist-info/METADATA
myelin-0.1.14.dist-info/WHEEL
myelin-0.1.14.dist-info/top_level.txt
myelin-0.1.14.dist-info/RECORD
